{
  "project_info": {
    "project_number": "707862758039",
    "project_id": "blue-ags",
    "storage_bucket": "blue-ags.appspot.com"
  },
  "client": [
    {
      "client_info": {
        "mobilesdk_app_id": "1:707862758039:android:27cbc1c05e0e87ea1d9fd2",
        "android_client_info": {
          "package_name": "com.example.blue"
        }
      },
      "oauth_client": [],
      "api_key": [
        {
          "current_key": "AIzaSyDDoCsruDQfyqNzKDVCkRbfZCIYkFy5mTI"
        }
      ],
      "services": {
        "appinvite_service": {
          "other_platform_oauth_client": []
        }
      }
    }
  ],
  "configuration_version": "1"
}